MANIFEST.in
README.rst
setup.py
django_scaffolding.egg-info/PKG-INFO
django_scaffolding.egg-info/SOURCES.txt
django_scaffolding.egg-info/dependency_links.txt
django_scaffolding.egg-info/not-zip-safe
django_scaffolding.egg-info/top_level.txt
scaffolding/__init__.py
scaffolding/models.py
scaffolding/tubes.py
scaffolding/external/__init__.py
scaffolding/external/facebook_graph.py
scaffolding/library/US_Top5000Population.csv
scaffolding/library/__init__.py
scaffolding/library/booktitles.py
scaffolding/library/cities.py
scaffolding/library/flickr.py
scaffolding/library/lorem_ipsum.py
scaffolding/library/names.py
scaffolding/library/top-10kURL.csv
scaffolding/library/url.py
scaffolding/management/__init__.py
scaffolding/management/commands/__init__.py
scaffolding/management/commands/scaffold.py