Metadata-Version: 1.1
Name: django-scaffolding
Version: 0.2.6
Summary: Automatically generate reasonable database entries for your app
Home-page: https://github.com/sbaechler/django-scaffolding/
Author: Simon Baechler
Author-email: simon@stellanera.com
License: MIT
Platform: UNKNOWN
Classifier: Environment :: Web Environment
Classifier: Framework :: Django
Classifier: Intended Audience :: Developers
Classifier: Operating System :: OS Independent
Classifier: Programming Language :: Python
Classifier: Programming Language :: Python :: 2
Classifier: Programming Language :: Python :: 2.6
Classifier: Programming Language :: Python :: 2.7
Classifier: Programming Language :: Python :: 3
Classifier: Programming Language :: Python :: 3.2
Classifier: Programming Language :: Python :: 3.3
